jsiiTimeAgo/_jsii/__init__.py
jsiiTimeAgo/_jsii/jsii-time-ago@0.0.1.jsii.tgz
jsiiTimeAgo-0.0.1.dist-info/LICENSE
jsiiTimeAgo-0.0.1.dist-info/METADATA
jsiiTimeAgo-0.0.1.dist-info/WHEEL
jsiiTimeAgo-0.0.1.dist-info/top_level.txt
jsiiTimeAgo-0.0.1.dist-info/RECORD
