Metadata-Version: 2.1
Name: jsiiTimeAgo
Version: 0.0.1
Summary: jsii-time-ago
Home-page: https://github.com/mbasadi/jsii-time-ago.git
Author: mbasadi<asadi.mohammadbagher@gmail.com>
License: Apache-2.0
Project-URL: Source, https://github.com/mbasadi/jsii-time-ago.git
Classifier: Intended Audience :: Developers
Classifier: Operating System :: OS Independent
Classifier: Programming Language :: JavaScript
Classifier: Programming Language :: Python :: 3 :: Only
Classifier: Programming Language :: Python :: 3.7
Classifier: Programming Language :: Python :: 3.8
Classifier: Programming Language :: Python :: 3.9
Classifier: Programming Language :: Python :: 3.10
Classifier: Typing :: Typed
Classifier: Development Status :: 5 - Production/Stable
Classifier: License :: OSI Approved
Requires-Python: ~=3.7
License-File: LICENSE
Requires-Dist: jsii (<2.0.0,>=1.69.0)
Requires-Dist: publication (>=0.0.3)
Requires-Dist: typeguard (~=2.13.3)
